MANIFEST.in
README.txt
setup.py
collective/__init__.py
collective.traverse.egg-info/PKG-INFO
collective.traverse.egg-info/SOURCES.txt
collective.traverse.egg-info/dependency_links.txt
collective.traverse.egg-info/entry_points.txt
collective.traverse.egg-info/namespace_packages.txt
collective.traverse.egg-info/not-zip-safe
collective.traverse.egg-info/requires.txt
collective.traverse.egg-info/top_level.txt
collective/traverse/__init__.py
collective/traverse/configure.zcml
collective/traverse/interfaces.py
collective/traverse/root.py
collective/traverse/tests.py
docs/AUTHOR.txt
docs/HISTORY.txt
docs/INSTALL.txt
docs/LICENSE.txt