Metadata-Version: 1.0
Name: collective.traverse
Version: 1.1
Summary: Traverse to Object by Interface
Home-page: http://www.brainson.de/
Author: Brainson New Media GmbH, D9T GmbH
Author-email: info@brainson.de
License: GPL
Platform: UNKNOWN
Classifier: Framework :: Plone
Classifier: Programming Language :: Python
Classifier: Topic :: Software Development :: Libraries :: Python Modules
